Verilog/Day 01/full_adder.v
module full_adder(
    input a, b, c,
    output s, cout
);
    assign s = a ^ b ^ c;
    assign cout = (a & b) | (b & c) | (a & c);

endmodule

Verilog/Day 01/full_adder_tb.v
`include "full_adder.v"
module full_adder_tb();
    reg a, b, c;
    wire s, cout;
    full_adder fa(a, b, c, s, cout);

    initial begin;
        $monitor("At time %0t: a=%b b=%b, sum=%b, carry=%b",$time, a, b, s, cout);
        $dumpfile("full_adder_tb.vcd");
        $dumpvars(0, full_adder_tb);
        a = 0; b = 0; c = 0;
        #1;
        a = 0; b = 0; c = 1;
        #1;
        a = 0; b = 1; c = 0;
        #1;
        a = 0; b = 1; c = 1;
        #1;
        a = 1; b = 0; c = 0;
        #1;
        a = 1; b = 0; c = 1;
        #1;
        a = 1; b = 1; c = 0;
        #1;
        a = 1; b = 1; c = 1;
        #1;
    end;

endmodule

Verilog/Day 01/full_adder_tb.vcd
$date
	Sat Jan 25 14:01:18 2025
$end
$version
	Icarus Verilog
$end
$timescale
	1s
$end
$scope module full_adder_tb $end
$var wire 1 ! s $end
$var wire 1 " cout $end
$var reg 1 # a $end
$var reg 1 $ b $end
$var reg 1 % c $end
$scope module fa $end
$var wire 1 # a $end
$var wire 1 $ b $end
$var wire 1 % c $end
$var wire 1 " cout $end
$var wire 1 ! s $end
$upscope $end
$upscope $end
$enddefinitions $end
#0
$dumpvars
0%
0$
0#
0"
0!
$end
#1
1!
1%
#2
0%
1$
#3
1"
0!
1%
#4
0"
1!
0%
0$
1#
#5
1"
0!
1%
#6
0%
1$
#7
1!
1%
